scace/__init__.py
scace/scace_train.py
scace/model/__init__.py
scace/model/merge_split.py
scace/model/scace_net.py
scace/util/__init__.py
scace/util/data_utils.py
scace/util/losses.py
scace/util/tools.py
scace-1.0.0.dist-info/LICENSE
scace-1.0.0.dist-info/METADATA
scace-1.0.0.dist-info/WHEEL
scace-1.0.0.dist-info/top_level.txt
scace-1.0.0.dist-info/RECORD
