Metadata-Version: 2.1
Name: scace
Version: 1.0.0
Summary: single-cell RNA-sequencing automatic clustering based on cluster merging
Home-page: https://github.com/sldyns
Author: Kun Qian, Xinwei He
Author-email: kun_qian@foxmail.com
Maintainer: Kun Qian
Maintainer-email: kun_qian@foxmail.com
License: MIT Licence
Keywords: single-cell RNA-sequencing,clustering,cluster merging
Platform: any
Requires-Dist: numpy
Requires-Dist: scanpy
Requires-Dist: torch
Requires-Dist: pandas
Requires-Dist: tqdm
Requires-Dist: scipy
Requires-Dist: sklearn
